{
  "project_info": {
    "project_number": "609407461041",
    "firebase_url": "https://parking-ef28a-default-rtdb.firebaseio.com",
    "project_id": "parking-ef28a",
    "storage_bucket": "parking-ef28a.appspot.com"
  },
  "client": [
    {
      "client_info": {
        "mobilesdk_app_id": "1:609407461041:android:863e6124de9e1a0c262490",
        "android_client_info": {
          "package_name": "com.example.parking"
        }
      },
      "oauth_client": [],
      "api_key": [
        {
          "current_key": "AIzaSyAeFwj7X-wFnaxypcGr7t3peJ7v6IZIDaQ"
        }
      ],
      "services": {
        "appinvite_service": {
          "other_platform_oauth_client": []
        }
      }
    }
  ],
  "configuration_version": "1"
}